benchmarks/__init__.py
benchmarks/benchmark_autodiff.py
marginaleffects/__init__.py
marginaleffects/_input_utils.py
marginaleffects/by.py
marginaleffects/classes.py
marginaleffects/comparisons.py
marginaleffects/datagrid.py
marginaleffects/docs.py
marginaleffects/equivalence.py
marginaleffects/estimands.py
marginaleffects/formulaic_utils.py
marginaleffects/hypotheses.py
marginaleffects/hypotheses_joint.py
marginaleffects/hypothesis.py
marginaleffects/hypothesis_formula.py
marginaleffects/inject_docs.py
marginaleffects/jax_dispatch.py
marginaleffects/model_abstract.py
marginaleffects/predictions.py
marginaleffects/result.py
marginaleffects/sanitize_model.py
marginaleffects/sanity.py
marginaleffects/settings.py
marginaleffects/slopes.py
marginaleffects/transform.py
marginaleffects/uncertainty.py
marginaleffects/utils.py
marginaleffects/validation.py
marginaleffects/autodiff/__init__.py
marginaleffects/autodiff/comparisons.py
marginaleffects/autodiff/utils.py
marginaleffects/autodiff/glm/__init__.py
marginaleffects/autodiff/glm/comparisons.py
marginaleffects/autodiff/glm/families.py
marginaleffects/autodiff/glm/predictions.py
marginaleffects/autodiff/linear/__init__.py
marginaleffects/autodiff/linear/comparisons.py
marginaleffects/autodiff/linear/predictions.py
marginaleffects/linearmodels/__init__.py
marginaleffects/linearmodels/model.py
marginaleffects/plot/__init__.py
marginaleffects/plot/common.py
marginaleffects/plot/comparisons.py
marginaleffects/plot/predictions.py
marginaleffects/plot/slopes.py
marginaleffects/pyfixest/__init__.py
marginaleffects/pyfixest/model.py
marginaleffects/sklearn/__init__.py
marginaleffects/sklearn/model.py
marginaleffects/statsmodels/__init__.py
marginaleffects/statsmodels/model.py
tests/__init__.py
tests/helpers.py
tests/test_analytic.py
tests/test_autodiff.py
tests/test_bugfix.py
tests/test_by.py
tests/test_categorical.py
tests/test_categorical_validation.py
tests/test_comparisons.py
tests/test_comparisons_interaction.py
marginaleffects-0.3.0.dist-info/METADATA
marginaleffects-0.3.0.dist-info/WHEEL
marginaleffects-0.3.0.dist-info/top_level.txt
marginaleffects-0.3.0.dist-info/RECORD
