Metadata-Version: 2.4
Name: marginaleffects
Version: 0.3.0
Summary: Predictions, counterfactual comparisons, slopes, and hypothesis tests for statistical models.
License-Expression: GPL-3.0-or-later
Requires-Python: >=3.10
Requires-Dist: formulaic>=1.0.2
Requires-Dist: narwhals>=1.34.0
Requires-Dist: numpy>=2.0.0
Requires-Dist: patsy>=1.0.1
Requires-Dist: polars>=1.26.0
Requires-Dist: pydantic>=2.10.3
Requires-Dist: plotnine>=0.14.5
Requires-Dist: scipy>=1.14.1
Requires-Dist: pyarrow>=19.0.1
Provides-Extra: autodiff
Requires-Dist: jax>=0.4.0; extra == "autodiff"
Provides-Extra: test
Requires-Dist: duckdb>=1.1.2; extra == "test"
Requires-Dist: matplotlib>=3.7.1; extra == "test"
Requires-Dist: linearmodels>=6.1; extra == "test"
Requires-Dist: pandas>=2.2.2; extra == "test"
Requires-Dist: pre-commit>=4.2.0; extra == "test"
Requires-Dist: pyarrow>=17.0.0; extra == "test"
Requires-Dist: pyfixest>=0.28.0; extra == "test"
Requires-Dist: statsmodels>=0.14.0; extra == "test"
Requires-Dist: scikit-learn; extra == "test"
Requires-Dist: typing-extensions>=4.7.0; extra == "test"
Requires-Dist: xgboost; extra == "test"
